emojichem/__init__.py
emojichem/data.py
emojichem/version.py
emojichem-0.3.0.dist-info/METADATA
emojichem-0.3.0.dist-info/WHEEL
emojichem-0.3.0.dist-info/top_level.txt
emojichem-0.3.0.dist-info/RECORD
