Metadata-Version: 2.1
Name: emojichem
Version: 0.3.0
Summary: Replace elements with emojis in rdkit
Home-page: https://github.com/whitead/emojichem
Author: Andrew White
Author-email: andrew.white@rochester.edu
License: MIT
Classifier: Programming Language :: Python :: 3
Classifier: License :: OSI Approved :: MIT License
Classifier: Operating System :: OS Independent
Requires-Dist: rdkit
Requires-Dist: skunk
